{
  "hash": "482b3d40",
  "browserHash": "1c6765ed",
  "optimized": {
    "vue": {
      "src": "../../../../node_modules/vue/dist/vue.runtime.esm-bundler.js",
      "file": "vue.js",
      "fileHash": "1d54ea70",
      "needsInterop": false
    },
    "xmind-embed-viewer": {
      "src": "../../../../node_modules/xmind-embed-viewer/dist/esm/index.js",
      "file": "xmind-embed-viewer.js",
      "fileHash": "548d4501",
      "needsInterop": false
    },
    "@mdit-vue/shared": {
      "src": "../../../../node_modules/@mdit-vue/shared/dist/index.mjs",
      "file": "@mdit-vue_shared.js",
      "fileHash": "6a3c9a26",
      "needsInterop": false
    }
  },
  "chunks": {
    "chunk-2B2CG5KL": {
      "file": "chunk-2B2CG5KL.js"
    }
  }
}